{
  "uuid": "78464c3b-a06f-446a-a73f-b64a4c9d9204",
  "shortName": "korean_watchface",
  "longName": "korean_watchface",
  "companyName": "MakeAwesomeHappen",
  "versionLabel": "1.0",
  "sdkVersion": "3",
  "targetPlatforms": ["aplite", "basalt"],
  "watchapp": {
    "watchface": true
  },
  "appKeys": {
    "dummy": 0
  },
  "resources": {
    "media": [
      { "type": "png", "name": "A", "file": "images/a.png" },
      { "type": "png", "name": "BUN", "file": "images/bun.png" },
      { "type": "png", "name": "CHIL", "file": "images/chil.png" },
      { "type": "png", "name": "DA", "file": "images/da.png" },
      { "type": "png", "name": "DU", "file": "images/du.png" },
      { "type": "png", "name": "DUL", "file": "images/dul.png" },
      { "type": "png", "name": "GONG", "file": "images/gong.png" },
      { "type": "png", "name": "GOPE", "file": "images/gope.png" },
      { "type": "png", "name": "HAN", "file": "images/han.png" },
      { "type": "png", "name": "HOA", "file": "images/hoa.png" },
      { "type": "png", "name": "HOPE", "file": "images/hope.png" },
      { "type": "png", "name": "IL", "file": "images/il.png" },
      { "type": "png", "name": "KU", "file": "images/ku.png" },
      { "type": "png", "name": "KUM", "file": "images/kum.png" },
      { "type": "png", "name": "MOK", "file": "images/mok.png" },
      { "type": "png", "name": "NEH", "file": "images/neh.png" },
      { "type": "png", "name": "O", "file": "images/o.png" },
      { "type": "png", "name": "PAL", "file": "images/pal.png" },
      { "type": "png", "name": "SA", "file": "images/sa.png" },
      { "type": "png", "name": "SAM", "file": "images/sam.png" },
      { "type": "png", "name": "SEH", "file": "images/seh.png" },
      { "type": "png", "name": "SHIP", "file": "images/ship.png" },
      { "type": "png", "name": "SI", "file": "images/si.png" },
      { "type": "png", "name": "SU", "file": "images/su.png" },
      { "type": "png", "name": "SUH", "file": "images/suh.png" },
      { "type": "png", "name": "TO", "file": "images/to.png" },
      { "type": "png", "name": "WUL", "file": "images/wul.png" },
      { "type": "png", "name": "YEUH", "file": "images/yeuh.png" },
      { "type": "png", "name": "YI", "file": "images/yi.png" },
      { "type": "png", "name": "YO", "file": "images/yo.png" },
      { "type": "png", "name": "YU", "file": "images/yu.png" },
      { "type": "png", "name": "YUK", "file": "images/yuk.png" },
      { "type": "png", "name": "YUL", "file": "images/yul.png" }
    ]
  }
}
